README.rst
setup.py
django_multidomain.egg-info/PKG-INFO
django_multidomain.egg-info/SOURCES.txt
django_multidomain.egg-info/dependency_links.txt
django_multidomain.egg-info/top_level.txt
multidomain/__init__.py
multidomain/middleware.py