Metadata-Version: 1.1
Name: django-multidomain
Version: 1.1.3
Summary: Django application, set urls per domain.
Home-page: https://github.com/cyacarinic/django-multidomain
Author: Claudio Yacarini
Author-email: cyacarinic@gmail.com
License: UNKNOWN
Keywords: django url domain host multi
Platform: UNKNOWN
Classifier: Development Status :: 4 - Beta
Classifier: Environment :: Web Environment
Classifier: Framework :: Django
Classifier: Intended Audience :: Developers
Classifier: Operating System :: OS Independent
Classifier: Programming Language :: Python
Classifier: Programming Language :: Python :: 2.7
Classifier: Topic :: Internet :: WWW/HTTP
Classifier: Topic :: Internet :: WWW/HTTP :: Dynamic Content
Classifier: Topic :: Internet :: WWW/HTTP :: WSGI
Classifier: Topic :: Software Development :: Libraries :: Application Frameworks
Classifier: Topic :: Software Development :: Libraries :: Python Modules
